MIPS32.srcs/sources_1/new/pipe_mips32.v
`timescale 1ns / 1ps
module pipe_mips32(
    input clk1,
    input clk2,
    output [31:0] out
    );
    
    //32-bit registers
    //General registers
    reg [31:0] PC;
    
    //Stage IF_ID registers
    reg [31:0] IF_ID_IR, IF_ID_NPC;
    
    //Stage ID_EX registers
    reg [31:0] ID_EX_IR, ID_EX_NPC, ID_EX_A, ID_EX_B, ID_EX_Imm;
    
    //Stage EX_MEM registers
    reg [31:0] EX_MEM_IR, EX_MEM_NPC, EX_MEM_B, EX_MEM_ALUout;
    
    //Stage MEM_WB registers
    reg [31:0] MEM_WB_IR, MEM_WB_ALUout, MEM_WB_LMD;
    
    //3-bit register
    reg [2:0] ID_EX_type, EX_MEM_type, MEM_WB_type;
    
    //1-bit registers
    reg EX_MEM_cond, HALTED, TAKEN_BRANCH;
    
    //Packed arrays
    reg [31:0] r_bank [0:31];
    reg [31:0] mem [0:1023];
    
    //Instruction parameters
    parameter ADD=6'b000000, SUB=6'b000001, AND=6'b000010, OR=6'b000011, SLT=6'b000100, MUL=6'b000101, LW=6'b001000, SW=6'b001001, ADDI=6'b001010, SUBI=6'b001011, SLTI=6'b001100, BNEQZ=6'b001101, BEQZ=6'b001110, HLT=6'b111111;
    
    //Type parameters
    parameter RR_ALU=3'b000, RM_ALU=3'b001, LOAD=3'b010, STORE=3'b011, BRANCH=3'b100, HALT=3'b101;
    
    //IF Stage
    always @(posedge clk1) begin
        if (HALTED == 0)
            begin
                if (((EX_MEM_IR[31:26] == BEQZ) && (EX_MEM_cond == 1)) || ((EX_MEM_IR[31:26] == BNEQZ) && (EX_MEM_cond == 0)))
                    begin
                        IF_ID_IR     <= #2 mem[EX_MEM_ALUout];
                        TAKEN_BRANCH <= #2 1'b1;
                        IF_ID_NPC    <= #2 EX_MEM_ALUout ;
                        PC           <= #2 EX_MEM_ALUout ;
                    end
                else begin
                    IF_ID_IR  <= #2 mem[PC];
                    IF_ID_NPC <= #2 PC + 1;
                    PC        <= #2 PC + 1;
                end
            end
        end
        
    //ID Stage
    always @(posedge clk2) begin
        if(HALTED==0) begin
            if (IF_ID_IR[25:21]==5'b00000) ID_EX_A <= 0          ;
            else ID_EX_A <= #2 r_bank[IF_ID_IR[25:21]]           ;
            
            if (IF_ID_IR[20:16]==5'b00000) ID_EX_B <= 0          ;
            else ID_EX_B <= #2 r_bank[IF_ID_IR[20:16]]           ;
            
            ID_EX_Imm <= #2 {{16{IF_ID_IR[15]}},{IF_ID_IR[15:0]}};
            ID_EX_NPC <= #2 IF_ID_NPC                            ;
            ID_EX_IR  <= #2 IF_ID_IR                             ;
            case(IF_ID_IR[31:26])
                ADD,SUB,AND,OR,MUL,SLT : ID_EX_type <= #2 RR_ALU ;
                LW                     : ID_EX_type <= #2 LOAD   ;
                SW                     : ID_EX_type <= #2 STORE  ;
                HLT                    : ID_EX_type <= #2 HALT   ;
                BEQZ,BNEQZ             : ID_EX_type <= #2 BRANCH ;
                ADDI,SUBI,SLTI         : ID_EX_type <= #2 RM_ALU ;
                default                : ID_EX_type <= #2 HALT   ;
            endcase
        end
    end
    
    //EX Stage
    always @(posedge clk1) begin
        if (HALTED==0) begin
            EX_MEM_IR     <= #2 ID_EX_IR;
            //EX_MEM_B      <= #2 ID_EX_B;         FUCK YOU
            EX_MEM_type   <= #2 ID_EX_type;
            TAKEN_BRANCH  <= #2 1'b0;
            
            case(ID_EX_type)
                RR_ALU: begin
                    case(ID_EX_IR[31:26])
                        ADD    : EX_MEM_ALUout <= #2 ID_EX_A + ID_EX_B;
                        SUB    : EX_MEM_ALUout <= #2 ID_EX_A - ID_EX_B;
                        AND    : EX_MEM_ALUout <= #2 ID_EX_A & ID_EX_B;
                        OR     : EX_MEM_ALUout <= #2 ID_EX_A | ID_EX_B;
                        SLT    : EX_MEM_ALUout <= #2 ID_EX_A < ID_EX_B;
                        MUL    : EX_MEM_ALUout <= #2 ID_EX_A * ID_EX_B;
                        default: EX_MEM_ALUout <= #2 32'hxxxxxxxx;
                    endcase
                end
                RM_ALU: begin
                    case(ID_EX_IR[31:26])
                        ADDI   : EX_MEM_ALUout <= #2 ID_EX_A + ID_EX_Imm;
                        SUB    : EX_MEM_ALUout <= #2 ID_EX_A - ID_EX_Imm;
                        SLTI   : EX_MEM_ALUout <= #2 ID_EX_A < ID_EX_Imm;
                        default: EX_MEM_ALUout <= #2 32'hxxxxxxxx;
                    endcase
                end
                LOAD,STORE: begin
                    EX_MEM_ALUout <= #2 ID_EX_A + ID_EX_Imm;
                    EX_MEM_B      <= #2 ID_EX_B;
                end
                BRANCH: begin
                    EX_MEM_ALUout <= #2 ID_EX_NPC + ID_EX_Imm;
                    EX_MEM_cond   <= #2 (ID_EX_A==0);
                end
            endcase
        end
    end
    
    //MEM Stage
    always @(posedge clk2) begin
        if(HALTED==0) begin
            MEM_WB_IR     <= #2 EX_MEM_IR;
            MEM_WB_type   <= #2 EX_MEM_type;
            case(EX_MEM_type)
                RR_ALU,RM_ALU : MEM_WB_ALUout <= #2 EX_MEM_ALUout;
                LOAD          : MEM_WB_LMD <= #2 mem[EX_MEM_ALUout];
                STORE         : if(TAKEN_BRANCH==0) mem[EX_MEM_ALUout] <= #2 EX_MEM_B;//FUCK YOU
            endcase
        end
    end
    
    //WB Stage
    always @(posedge clk1) begin
        if (TAKEN_BRANCH==0) begin
            case(MEM_WB_type)
                RR_ALU : r_bank[MEM_WB_IR[15:11]] <= #2 MEM_WB_ALUout;
                RM_ALU : r_bank[MEM_WB_IR[20:16]] <= #2 MEM_WB_ALUout;
                LOAD   : r_bank[MEM_WB_IR[20:16]] <= #2 MEM_WB_LMD;
                HALT   : HALTED <= #2 1'b1;
            endcase
        end
    end
    assign out = MEM_WB_ALUout;
endmodule

MIPS32.srcs/sim_1/new/test_mips32.v
`timescale 1ns / 1ps
module test_mips32;
reg clk1, clk2;

  integer k;

  pipe_mips32 mips(clk1, clk2);

  initial begin
    clk1 = 0;
    clk2 = 0;

    // Slower clock for debugging
    repeat (20) begin
      #10 clk1 = ~clk1;
      #10 clk2 = ~clk2;
    end
  end
initial
    begin
        for(k=0; k<31; k=k+1) 
            mips.r_bank[k]=k;
        mips.mem[0] = 32'h2801000a;                   //ADDI R1,R0,10
        mips.mem[1] = 32'h28020014;                   //ADDI R2,R0,20
        mips.mem[2] = 32'h28030019;                   //ADDI R3,R0,25
        mips.mem[3] = 32'h0ce77800;                   //OR R7,R7,R7
        mips.mem[4] = 32'h0ce77800;                   //OR R7,R7,R7
        mips.mem[5] = 32'h00222000;                   //ADDI R4,R1,R2
        mips.mem[6] = 32'h0ce77800;                   //OR R7,R7,R7
        mips.mem[7] = 32'h00832800;                   //ADDI R5,R4,R3
        mips.mem[8] = 32'hfc000000;                   //HLT
        mips.HALTED = 0;
        mips.PC = 0;
        mips.TAKEN_BRANCH = 0;
        
        #500
        for (k=0; k<6; k=k+1) $display ("R%1d - %2d", k, mips.r_bank[k]);
    end
initial begin
    $dumpfile ("mips.vcd");
    $dumpvars(0, test_mips32);
    #600 $finish;
end
endmodule

MIPS32.sim/sim_1/behav/xsim/mips.vcd
$date
   Fri Aug  2 23:40:50 2024
$end

$version
  2024.1
  $dumpfile ("mips.vcd") 
$end

$timescale
  1ps
$end

$scope module test_mips32 $end
$var reg 1 ! clk1 $end
$var reg 1 " clk2 $end
$var integer 32 # k [31:0] $end
$scope module mips $end
$var wire 1 $ clk1 $end
$var wire 1 % clk2 $end
$var wire 32 & out [31:0] $end
$var reg 32 ' PC [31:0] $end
$var reg 32 ( IF_ID_IR [31:0] $end
$var reg 32 ) IF_ID_NPC [31:0] $end
$var reg 32 * ID_EX_IR [31:0] $end
$var reg 32 + ID_EX_NPC [31:0] $end
$var reg 32 , ID_EX_A [31:0] $end
$var reg 32 - ID_EX_B [31:0] $end
$var reg 32 . ID_EX_Imm [31:0] $end
$var reg 32 / EX_MEM_IR [31:0] $end
$var reg 32 0 EX_MEM_NPC [31:0] $end
$var reg 32 1 EX_MEM_B [31:0] $end
$var reg 32 2 EX_MEM_ALUout [31:0] $end
$var reg 32 3 MEM_WB_IR [31:0] $end
$var reg 32 4 MEM_WB_ALUout [31:0] $end
$var reg 32 5 MEM_WB_LMD [31:0] $end
$var reg 3 6 ID_EX_type [2:0] $end
$var reg 3 7 EX_MEM_type [2:0] $end
$var reg 3 8 MEM_WB_type [2:0] $end
$var reg 1 9 EX_MEM_cond $end
$var reg 1 : HALTED $end
$var reg 1 ; TAKEN_BRANCH $end
$upscope $end
$upscope $end
$enddefinitions $end

#0
$dumpvars
0!
0"
b11111 #
0$
0%
bx &
b0 '
bx (
bx )
bx *
bx +
bx ,
bx -
bx .
bx /
bx 0
bx 1
bx 2
bx 3
bx 4
bx 5
bx 6
bx 7
bx 8
x9
0:
0;
$end

#10000
1!
1$

#12000
b1 '
b101000000000010000000001111000 (
b1 )

#20000
1"
1%
b0 ,

#22000
b101000000000010000000001111000 *
b1 +
b1 -
b1111000 .
b1 6

#30000
0!
0$

#40000
0"
0%

#50000
1!
1$

#52000
b10 '
b1100011000110001100000000000 (
b10 )
b101000000000010000000001111000 /
b1111000 2
b1 7

#60000
1"
1%

#62000
b1111000 &
b1100011000110001100000000000 *
b10 +
b11 ,
b11 -
b1100000000000 .
b101000000000010000000001111000 3
b1111000 4
b0 6
b1 8

#70000
0!
0$

#80000
0"
0%

#90000
1!
1$

#92000
b11 '
b100000001000100000000000000000 (
b11 )
b1100011000110001100000000000 /
b11 2
b0 7

#100000
1"
1%

#102000
b11 &
b100000001000100000000000000000 *
b11 +
b1111000 ,
b10 -
b0 .
b1100011000110001100000000000 3
b11 4
b10 6
b0 8

#110000
0!
0$

#120000
0"
0%

#130000
1!
1$

#132000
b100 '
b1100011000110001100000000000 (
b100 )
b100000001000100000000000000000 /
b10 1
b1111000 2
b10 7

#140000
1"
1%

#142000
b1100011000110001100000000000 *
b100 +
b11 ,
b11 -
b1100000000000 .
b100000001000100000000000000000 3
b1010101 5
b0 6
b10 8

#150000
0!
0$

#160000
0"
0%

#170000
1!
1$

#172000
b101 '
b101000010000100000000000101101 (
b101 )
b1100011000110001100000000000 /
b11 2
b0 7

#180000
1"
1%

#182000
b101000010000100000000000101101 *
b101 +
b1010101 ,
b1010101 -
b101101 .
b1100011000110001100000000000 3
b1 6
b0 8

#190000
0!
0$

#200000
0"
0%

#210000
1!
1$

#212000
b110 '
b1100011000110001100000000000 (
b110 )
b101000010000100000000000101101 /
b10000010 2
b1 7

#220000
1"
1%

#222000
b10000010 &
b1100011000110001100000000000 *
b110 +
b11 ,
b11 -
b1100000000000 .
b101000010000100000000000101101 3
b10000010 4
b0 6
b1 8

#230000
0!
0$

#240000
0"
0%

#250000
1!
1$

#252000
b111 '
b100100001000100000000000000001 (
b111 )
b1100011000110001100000000000 /
b11 2
b0 7

#260000
1"
1%

#262000
b11 &
b100100001000100000000000000001 *
b111 +
b1111000 ,
b10000010 -
b1 .
b1100011000110001100000000000 3
b11 4
b11 6
b0 8

#270000
0!
0$

#280000
0"
0%

#290000
1!
1$

#292000
b1000 '
b11111100000000000000000000000000 (
b1000 )
b100100001000100000000000000001 /
b10000010 1
b1111001 2
b11 7

#300000
1"
1%
b0 ,
b0 -

#302000
b11111100000000000000000000000000 *
b1000 +
b0 .
b100100001000100000000000000001 3
b101 6
b11 8

#310000
0!
0$

#320000
0"
0%

#330000
1!
1$

#332000
b1001 '
bx (
b1001 )
b11111100000000000000000000000000 /
b101 7

#340000
1"
1%

#342000
bx *
b1001 +
bx ,
bx -
bx .
b11111100000000000000000000000000 3
b101 8

#350000
0!
0$

#360000
0"
0%

#370000
1!
1$

#372000
b1010 '
b1010 )
bx /
1:

